netease_encode_api/__init__.py
netease_encode_api/global_args.py
netease_encode_api-1.2.3.dist-info/licenses/LICENSE
netease_encode_api-1.2.3.dist-info/METADATA
netease_encode_api-1.2.3.dist-info/WHEEL
netease_encode_api-1.2.3.dist-info/top_level.txt
netease_encode_api-1.2.3.dist-info/RECORD
