Metadata-Version: 2.4
Name: netease-encode-api
Version: 1.2.3
Summary: 网易云weapi解码和封装。
Author-email: CooooldWind_ <3091868003@qq.com>
License: AGPL-3.0-or-later
Requires-Python: >=3.9
License-File: LICENSE
Requires-Dist: pycryptodome~=3.23.0
Requires-Dist: pyqrcode~=1.2.1
Requires-Dist: requests~=2.32.4
Dynamic: license-file
